MANIFEST.in
orchlib.py
setup.py
waf
wscript
examples/dumpenv.cfg
examples/env.cfg
examples/externals.cfg
examples/gnuprograms.cfg
examples/recur.cfg
examples/simple.cfg
examples/tbb.cfg
examples/test_deconf.cfg
examples/test_deconf_includeme.cfg
examples/test_deconf_main.cfg
examples/test_deconf_main2.cfg
examples/test_dumpenv.cfg
examples/test_envmunge.cfg
examples/dayabay/racf.cfg
examples/g4root/all.cfg
examples/g4root/defaults.cfg
examples/g4root/geant.cfg
examples/g4root/root.cfg
examples/include/test_deconf_includeme2.cfg
examples/python/main.cfg
examples/simple/buildtools.cfg
examples/simple/gnuprograms.cfg
examples/simple/simple.cfg
examples/simple-with-modules/main.cfg
examples/simple-with-patch/gnuprograms.cfg
examples/simple-with-patch/simple.cfg
examples/tests/vcs/vcs.cfg
orch/__init__.py
orch/build.py
orch/configure.py
orch/confnode.py
orch/deconf.py
orch/dot.py
orch/envmunge.py
orch/graph.py
orch/hostinfo.py
orch/mungers.py
orch/pkgconf.py
orch/rootsys.py
orch/tools.py
orch/ups.py
orch/util.py
orch/wafutil.py
orch/features/__init__.py
orch/features/feature_command.py
orch/features/feature_dlrun.py
orch/features/feature_download.py
orch/features/feature_dumpenv.py
orch/features/feature_makemake.py
orch/features/feature_patch.py
orch/features/feature_prepare.py
orch/features/feature_pypackage.py
orch/features/feature_tarball.py
orch/features/feature_tarpack.py
orch/features/feature_unpack.py
orch/features/feature_vcs.py
worch/__init__.py
worch.egg-info/PKG-INFO
worch.egg-info/SOURCES.txt
worch.egg-info/dependency_links.txt
worch.egg-info/top_level.txt
worch/extras/__init__.py
worch/extras/fnal.py
worch/extras/modulesfile.py
worch/extras/pythia6.py
worch/extras/tbbinst.py