Metadata-Version: 1.0
Name: worch
Version: 1.3.3
Summary: Build orchestration with waf.
Home-page: http://github.com/brettviren/worch
Author: Brett Viren
Author-email: brett.viren@gmail.com
License: GPLv2
Platform: UNKNOWN
